{"indexed":{"date-parts":[[2024,8,10]],"date-time":"2024-08-10T11:52:35Z","timestamp":1723290755569},"reference-count":64,"publisher":"Wiley","issue":"12","license":[{"start":{"date-parts":[[2020,9,23]],"date-time":"2020-09-23T00:00:00Z","timestamp":1600819200000},"content-version":"vor","delay-in-days":0,"URL":"http:\/\/onlinelibrary.wiley.com\/termsAndConditions#vor"}],"content-domain":{"domain":["besjournals.onlinelibrary.wiley.com"],"crossmark-restriction":true},"published-print":{"date-parts":[[2020,12]]},"abstract":"<jats:title>Abstract<\/jats:title><jats:p>\n<jats:list>\n\n<jats:list-item><jats:p>One of the best\u2010known biogeographic rules for ectotherms is the temperature\u2010size rule, which asserts that ectotherms produce smaller adults at warmer temperatures. Although this is often true, it has become clear that there is no single process behind the pattern and many exceptions to the rule. To disentangle such complex temperature\u2013size relationships, individual clades must be examined at ecological and evolutionary scales.<\/jats:p><\/jats:list-item>\n\n<jats:list-item><jats:p>We examined temperature\u2013size relationships for 2,106 individuals from 64 populations and 40 species of <jats:italic>Cephaloleia<\/jats:italic> rolled\u2010leaf beetles (Chrysomelidae; Cassidinae) occurring along two tropical elevational gradients: Barva and the Talamanca Cordillera in Costa Rica, Central America. We tested whether the temperature\u2010size rule applied to interspecific elevational assemblages, intraspecific elevational populations or different rearing temperatures for individual populations.<\/jats:p><\/jats:list-item>\n\n<jats:list-item><jats:p>At the interspecific scale, evolutionary history, rather than elevation, explains body size. At the intraspecific scale, only one of seven species followed the temperature\u2013size rule across elevations. When larvae were reared at different temperatures, only one of five populations followed the temperature\u2013size rule. Most populations grew to a fixed size regardless of temperature.<\/jats:p><\/jats:list-item>\n\n<jats:list-item><jats:p>Size in <jats:italic>Cephaloleia<\/jats:italic> beetles is constrained by their evolutionary history and responds to factors that rarely correlate with temperature. As temperature increases, ectotherms will not universally shrink, but determining if and why their size will change will require further investigation.<\/jats:p><\/jats:list-item>\n<\/jats:list>\n<\/jats:p><jats:p>A free <jats:ext-link xmlns:xlink=\"http:\/\/www.w3.org\/1999\/xlink\" xlink:href=\"http:\/\/onlinelibrary.wiley.com\/doi\/10.1111\/1365-2435.13666\/suppinfo\">Plain Language Summary<\/jats:ext-link> can be found within the Supporting Information of this article.<\/jats:p>","DOI":"10.1111\/1365-2435.13666","type":"journal-article","created":{"date-parts":[[2020,8,26]],"date-time":"2020-08-26T19:04:26Z","timestamp":1598468666000},"page":"2513-2523","update-policy":"http:\/\/dx.doi.org\/10.1002\/crossmark_policy","source":"Crossref","is-referenced-by-count":10,"title":"Evolutionary history, not ecogeographic rules, explains size variation of tropical insects along elevational gradients","prefix":"10.1111","volume":"34","author":[{"ORCID":"http:\/\/orcid.org\/0000-0002-5112-4332","authenticated-orcid":false,"given":"Carlos","family":"Garcia\u2010Robledo","sequence":"first","affiliation":[{"name":"Department of Ecology and Evolutionary Biology University of Connecticut Storrs CT USA"}]},{"ORCID":"http:\/\/orcid.org\/0000-0001-6294-6780","authenticated-orcid":false,"given":"Christina S.","family":"Baer","sequence":"additional","affiliation":[{"name":"Department of Ecology and Evolutionary Biology University of Connecticut Storrs CT USA"}]},{"given":"Kes","family":"Lippert","sequence":"additional","affiliation":[{"name":"Department of Ecology and Evolutionary Biology University of Connecticut Storrs CT USA"}]},{"given":"Vikas","family":"Sarathy","sequence":"additional","affiliation":[{"name":"Department of Ecology and Evolutionary Biology University of Connecticut Storrs CT USA"}]}],"member":"311","published-online":{"date-parts":[[2020,9,23]]},"reference":[{"key":"e_1_2_9_2_1","doi-asserted-by":"publisher","DOI":"10.1017\/S0016672304007281"},{"key":"e_1_2_9_3_1","doi-asserted-by":"publisher","DOI":"10.1016\/S0065-2504(08)60212-3"},{"key":"e_1_2_9_4_1","first-page":"595","article-title":"\u00dcber die Verh\u00e4ltnisse der warmeokonomie der Thiere zu \u00fcber Grosse","volume":"3","author":"Bergmann C.","year":"1847","journal-title":"Gottinger Studien"},{"key":"e_1_2_9_5_1","doi-asserted-by":"publisher","DOI":"10.1111\/j.1365-2656.2005.01028.x"},{"key":"e_1_2_9_6_1","doi-asserted-by":"publisher","DOI":"10.1046\/j.1472-4642.1999.00046.x"},{"key":"e_1_2_9_7_1","doi-asserted-by":"publisher","DOI":"10.1093\/icb\/44.6.413"},{"key":"e_1_2_9_8_1","doi-asserted-by":"publisher","DOI":"10.1111\/ecog.03917"},{"key":"e_1_2_9_9_1","doi-asserted-by":"publisher","DOI":"10.1073\/pnas.1106556108"},{"key":"e_1_2_9_10_1","doi-asserted-by":"publisher","DOI":"10.1034\/j.1600-0587.2003.03479.x"},{"key":"e_1_2_9_11_1","doi-asserted-by":"publisher","DOI":"10.1371\/journal.pone.0122905"},{"key":"e_1_2_9_12_1","doi-asserted-by":"publisher","DOI":"10.1126\/science.1162547"},{"key":"e_1_2_9_13_1","doi-asserted-by":"publisher","DOI":"10.1073\/pnas.0902080106"},{"key":"e_1_2_9_14_1","doi-asserted-by":"publisher","DOI":"10.1093\/icb\/icj007"},{"key":"e_1_2_9_15_1","doi-asserted-by":"publisher","DOI":"10.1139\/cjz-2015-0168"},{"key":"e_1_2_9_16_1","doi-asserted-by":"publisher","DOI":"10.1111\/j.1365-313X.2006.02842.x"},{"key":"e_1_2_9_17_1","doi-asserted-by":"publisher","DOI":"10.7591\/9781501734571"},{"key":"e_1_2_9_18_1","article-title":"Data from: Evolutionary history, not ecogeographic rules, explains size variation of tropical insects along elevational gradients","author":"Garcia\u2010Robledo C.","year":"2020","journal-title":"Dryad Digital Repository"},{"key":"e_1_2_9_19_1","doi-asserted-by":"publisher","DOI":"10.1111\/j.1365-2656.2011.01843.x"},{"key":"e_1_2_9_20_1","doi-asserted-by":"publisher","DOI":"10.1111\/j.1420-9101.2011.02401.x"},{"key":"e_1_2_9_21_1","doi-asserted-by":"publisher","DOI":"10.11646\/zootaxa.2610.1.3"},{"key":"e_1_2_9_22_1","doi-asserted-by":"publisher","DOI":"10.1002\/ecs2.3083"},{"key":"e_1_2_9_23_1","doi-asserted-by":"publisher","DOI":"10.1073\/pnas.1507681113"},{"key":"e_1_2_9_24_1","doi-asserted-by":"publisher","DOI":"10.1111\/bij.12115"},{"key":"e_1_2_9_25_1","doi-asserted-by":"publisher","DOI":"10.1666\/07-089.1"},{"key":"e_1_2_9_26_1","doi-asserted-by":"publisher","DOI":"10.1016\/j.tree.2011.03.005"},{"key":"e_1_2_9_27_1","doi-asserted-by":"publisher","DOI":"10.1371\/journal.pone.0000360"},{"key":"e_1_2_9_28_1","volume-title":"The insects: An outline of entomology","author":"Gullan P. J.","year":"2014"},{"key":"e_1_2_9_29_1","first-page":"99","volume-title":"Biodiversity conservation in Costa Rica","author":"Haber W. A.","year":"2004"},{"key":"e_1_2_9_30_1","volume-title":"Manual de Plantas de Costa Rica","author":"Hammel B. E.","year":"2010"},{"key":"e_1_2_9_31_1","first-page":"185","article-title":"Altitudinal gradients in the body sizes of Costa Rican butterflies","volume":"17","author":"Hawkins B. A.","year":"1996","journal-title":"Acta Oecologica"},{"key":"e_1_2_9_32_1","doi-asserted-by":"publisher","DOI":"10.1016\/j.jtherbio.2014.12.003"},{"key":"e_1_2_9_33_1","doi-asserted-by":"publisher","DOI":"10.1126\/science.105.2727.367"},{"key":"e_1_2_9_34_1","doi-asserted-by":"publisher","DOI":"10.1111\/ele.12413"},{"key":"e_1_2_9_35_1","doi-asserted-by":"publisher","DOI":"10.1111\/1365-2435.13031"},{"key":"e_1_2_9_36_1","doi-asserted-by":"publisher","DOI":"10.2307\/1935374"},{"key":"e_1_2_9_37_1","doi-asserted-by":"publisher","DOI":"10.1086\/282487"},{"key":"e_1_2_9_38_1","first-page":"352","article-title":"Life history and demography of Cephaloleia fenestrata (Hispinae: Chrysomelidae: Coleoptera)","volume":"36","author":"Johnson D. M.","year":"2004","journal-title":"Biotropica"},{"key":"e_1_2_9_39_1","doi-asserted-by":"publisher","DOI":"10.1890\/03-0508"},{"key":"e_1_2_9_40_1","first-page":"251","article-title":"Size, temperature, and fitness: Three rules","volume":"10","author":"Kingsolver J. G.","year":"2008","journal-title":"Evolutionary Ecology Research"},{"key":"e_1_2_9_41_1","volume-title":"Biogeography","author":"Lomolino M. V.","year":"2006"},{"key":"e_1_2_9_42_1","doi-asserted-by":"publisher","DOI":"10.1016\/j.ympev.2005.06.011"},{"key":"e_1_2_9_43_1","doi-asserted-by":"publisher","DOI":"10.1109\/GCE.2010.5676129"},{"key":"e_1_2_9_44_1","doi-asserted-by":"publisher","DOI":"10.1111\/1365-2435.12098"},{"key":"e_1_2_9_45_1","doi-asserted-by":"publisher","DOI":"10.1093\/bioinformatics\/btg412"},{"key":"e_1_2_9_46_1","doi-asserted-by":"publisher","DOI":"10.1002\/jez.a.211"},{"key":"e_1_2_9_47_1","volume-title":"R: A language and environment for statistical computing","author":"R Core Team","year":"2016"},{"key":"e_1_2_9_48_1","doi-asserted-by":"publisher","DOI":"10.1126\/science.aax0149"},{"key":"e_1_2_9_49_1","doi-asserted-by":"publisher","DOI":"10.1111\/j.2041-210X.2011.00169.x"},{"key":"e_1_2_9_50_1","doi-asserted-by":"publisher","DOI":"10.1007\/BF00346461"},{"key":"e_1_2_9_51_1","article-title":"A new estimate of the average earth surface land temperature spanning 1753 to 2011","volume":"7","author":"Rohde R.","year":"2013","journal-title":"Geoinformatics & Geostatistics: An Overview"},{"key":"e_1_2_9_52_1","doi-asserted-by":"publisher","DOI":"10.1111\/j.0908-8857.2004.03297.x"},{"key":"e_1_2_9_53_1","volume-title":"RStudio: Integrated development for R","author":"RStudio Team","year":"2015"},{"key":"e_1_2_9_54_1","doi-asserted-by":"publisher","DOI":"10.1146\/annurev-ento-010715-023859"},{"key":"e_1_2_9_55_1","doi-asserted-by":"publisher","DOI":"10.1111\/j.1365-294X.2011.05156.x"},{"key":"e_1_2_9_56_1","doi-asserted-by":"publisher","DOI":"10.1086\/667595"},{"key":"e_1_2_9_57_1","doi-asserted-by":"publisher","DOI":"10.11646\/zootaxa.2033.1.6"},{"key":"e_1_2_9_58_1","doi-asserted-by":"publisher","DOI":"10.3897\/zookeys.436.5766"},{"key":"e_1_2_9_59_1","doi-asserted-by":"publisher","DOI":"10.2307\/1937243"},{"key":"e_1_2_9_60_1","doi-asserted-by":"publisher","DOI":"10.1371\/journal.pone.0022610"},{"key":"e_1_2_9_61_1","doi-asserted-by":"publisher","DOI":"10.1890\/10-2369.1"},{"key":"e_1_2_9_62_1","doi-asserted-by":"publisher","DOI":"10.1016\/j.cois.2020.06.001"},{"key":"e_1_2_9_63_1","doi-asserted-by":"publisher","DOI":"10.1007\/s10682-013-9664-9"},{"key":"e_1_2_9_64_1","doi-asserted-by":"publisher","DOI":"10.1126\/science.289.5477.291"},{"key":"e_1_2_9_65_1","doi-asserted-by":"publisher","DOI":"10.1111\/geb.12525"}],"container-title":"Functional Ecology","original-title":[],"language":"en","link":[{"URL":"https:\/\/onlinelibrary.wiley.com\/doi\/pdf\/10.1111\/1365-2435.13666","content-type":"application\/pdf","content-version":"vor","intended-application":"text-mining"},{"URL":"https:\/\/onlinelibrary.wiley.com\/doi\/full-xml\/10.1111\/1365-2435.13666","content-type":"application\/xml","content-version":"vor","intended-application":"text-mining"},{"URL":"https:\/\/besjournals.onlinelibrary.wiley.com\/doi\/pdf\/10.1111\/1365-2435.13666","content-type":"unspecified","content-version":"vor","intended-application":"similarity-checking"}],"deposited":{"date-parts":[[2023,9,5]],"date-time":"2023-09-05T02:35:12Z","timestamp":1693881312000},"score":1,"resource":{"primary":{"URL":"https:\/\/besjournals.onlinelibrary.wiley.com\/doi\/10.1111\/1365-2435.13666"}},"subtitle":[],"editor":[{"given":"Craig","family":"White","sequence":"additional","affiliation":[]}],"short-title":[],"issued":{"date-parts":[[2020,9,23]]},"references-count":64,"journal-issue":{"issue":"12","published-print":{"date-parts":[[2020,12]]}},"alternative-id":["10.1111\/1365-2435.13666"],"URL":"http:\/\/dx.doi.org\/10.1111\/1365-2435.13666","relation":{},"ISSN":["0269-8463","1365-2435"],"subject":[],"container-title-short":"Functional Ecology","published":{"date-parts":[[2020,9,23]]},"assertion":[{"value":"2020-02-10","order":0,"name":"received","label":"Received","group":{"name":"publication_history","label":"Publication History"}},{"value":"2020-08-13","order":1,"name":"accepted","label":"Accepted","group":{"name":"publication_history","label":"Publication History"}},{"value":"2020-09-23","order":2,"name":"published","label":"Published","group":{"name":"publication_history","label":"Publication History"}}]}