{"indexed":{"date-parts":[[2023,5,21]],"date-time":"2023-05-21T21:25:48Z","timestamp":1684704348378},"reference-count":59,"publisher":"Pensoft Publishers","license":[{"start":{"date-parts":[[2018,2,8]],"date-time":"2018-02-08T00:00:00Z","timestamp":1518048000000},"content-version":"vor","delay-in-days":0,"URL":"http:\/\/creativecommons.org\/licenses\/by\/4.0\/"}],"content-domain":{"domain":[],"crossmark-restriction":false},"DOI":"10.3897\/zookeys.736.20739","type":"journal-article","created":{"date-parts":[[2018,2,8]],"date-time":"2018-02-08T09:56:09Z","timestamp":1518083769000},"page":"79-118","source":"Crossref","is-referenced-by-count":10,"title":"Systematics of Phyllocnistis leaf-mining moths (Lepidoptera, Gracillariidae) feeding on dogwood (Cornus spp.) in Northeast Asia, with the description of three new species","prefix":"10.3897","volume":"736","author":[{"given":"Natalia","family":"Kirichenko","sequence":"first","affiliation":[]},{"given":"Paolo","family":"Triberti","sequence":"additional","affiliation":[]},{"given":"Shigeki","family":"Kobayashi","sequence":"additional","affiliation":[]},{"given":"Toshiya","family":"Hirowatari","sequence":"additional","affiliation":[]},{"ORCID":"http:\/\/orcid.org\/0000-0002-0418-4439","authenticated-orcid":true,"given":"Camiel","family":"Doorenweerd","sequence":"additional","affiliation":[]},{"given":"Issei","family":"Ohshima","sequence":"additional","affiliation":[]},{"given":"Guo-Hua","family":"Huang","sequence":"additional","affiliation":[]},{"given":"Min","family":"Wang","sequence":"additional","affiliation":[]},{"given":"Emmanuelle","family":"Magnoux","sequence":"additional","affiliation":[]},{"ORCID":"http:\/\/orcid.org\/0000-0003-2278-2368","authenticated-orcid":true,"given":"Carlos","family":"Lopez-Vaamonde","sequence":"additional","affiliation":[]}],"member":"2258","published-online":{"date-parts":[[2018,2,8]]},"reference":[{"key":"20739_B1","doi-asserted-by":"publisher","DOI":"10.18984\/lepid.62.2_75"},{"key":"20739_B2","doi-asserted-by":"publisher","DOI":"10.1128\/AEM.00731-06"},{"key":"20739_B3","author":"Barannik","year":"1981","journal-title":"Insects of the green plantations in industrial cities of the Kemerovo region."},{"key":"20739_B4","doi-asserted-by":"publisher","DOI":"10.5281\/zenodo.211012"},{"key":"20739_B5","doi-asserted-by":"publisher","DOI":"10.11646\/zootaxa.4341.3.1"},{"key":"20739_B6","doi-asserted-by":"publisher","DOI":"10.1111\/aen.12298"},{"key":"20739_B7","doi-asserted-by":"publisher","DOI":"10.1071\/ZO98048"},{"key":"20739_B8","first-page":"25","article-title":"Gracilliidae.","author":"Davis","year":"1984","journal-title":"Part 1. Dr. W. Junk Publishers, The Hague"},{"key":"20739_B9","doi-asserted-by":"publisher","DOI":"10.3897\/zookeys.97.753"},{"key":"20739_B10","doi-asserted-by":"publisher","DOI":"10.3897\/zookeys.97.753"},{"key":"20739_B11","author":"De Prins","year":"2017"},{"issue":"2","key":"20739_B12","first-page":"113","article-title":"On the taxonomic history of Phyllocnistis Zeller, 1848 (Gracillariidae).","volume":"32","author":"De Prins","year":"2009","journal-title":"Nota Lepidopterologica"},{"key":"20739_B13","author":"Doorenweerd","year":"2017"},{"key":"20739_B14","doi-asserted-by":"publisher","DOI":"10.3897\/zookeys.422.7446"},{"key":"20739_B15","doi-asserted-by":"publisher","DOI":"10.1111\/syen.12212"},{"key":"20739_B16","author":"Drake","year":"2009"},{"key":"20739_B17","first-page":"125","article-title":"Phyllocnistidae from the Far East with descriptions of two new species.","author":"Ermolaev","year":"1987","journal-title":"Far East Scientific Center, Vladivostok: 37\u201340"},{"key":"20739_B18","doi-asserted-by":"publisher","DOI":"10.1016\/j.rbe.2017.11.001"},{"key":"20739_B19","first-page":"294","article-title":"DNA primers for amplification of mitochondrial cytochrome c oxidase subunit I from diverse metazoan invertebrates.","volume":"3","author":"Folmer","year":"1994","journal-title":"Molecular Marine Biology and Biotechnology"},{"key":"20739_B20","doi-asserted-by":"publisher","DOI":"10.1098\/rspb.2002.2218"},{"key":"20739_B21","doi-asserted-by":"publisher","DOI":"10.3897\/zookeys.586.8375"},{"issue":"2","key":"20739_B22","first-page":"257","article-title":"Resource partitioning among three willow leaf miners: consequence of hostplant phenology.","volume":"4","author":"Kagata","year":"2001","journal-title":"Entomological Science"},{"key":"20739_B23","doi-asserted-by":"publisher","DOI":"10.3897\/zookeys.27.250"},{"key":"20739_B24","doi-asserted-by":"publisher","DOI":"10.1111\/syen.12210"},{"key":"20739_B25","first-page":"235","article-title":"Methodological approaches to the study of insects mining leaves of woody plants.","volume":"207","author":"Kirichenko","year":"2014","journal-title":"Transactions of Saint Petersburg State Forest Technical Academy (Izvestia Sankt-Peterburgskoj Lesotehniceskoj Akademii)"},{"key":"20739_B26","doi-asserted-by":"publisher","DOI":"10.3897\/zookeys.473.8543"},{"key":"20739_B27","doi-asserted-by":"publisher","DOI":"10.3897\/zookeys.579.7166"},{"key":"20739_B28","first-page":"115","article-title":"Lepidoptera.","author":"Klots","year":"1970","journal-title":"(Second revised and enlarged edition). Munksgaard, Copenhagen"},{"key":"20739_B29","doi-asserted-by":"publisher","DOI":"10.18984\/lepid.62.4_156"},{"key":"20739_B30","author":"Kobayashi","year":"2013"},{"key":"20739_B31","doi-asserted-by":"publisher","DOI":"10.5281\/zenodo.204720"},{"key":"20739_B32","doi-asserted-by":"publisher","DOI":"10.18984\/lepid.62.2_75"},{"key":"20739_B33","doi-asserted-by":"publisher","DOI":"10.1002\/ece3.886"},{"key":"20739_B34","author":"Koropachinskiy","year":"2012","journal-title":"Woody plants of the Asian part of Russia."},{"key":"20739_B35","author":"Kuroko","year":"1982"},{"issue":"3","key":"20739_B36","first-page":"625","article-title":"Evolutionary-morphological approach to the systematics of leafminers of the genus Phyllonorycter Hbn. (Lepidoptera, Gracillariidae) with account of species feeding specialization.","volume":"83","author":"Kuznetzov","year":"2004","journal-title":"Entomologicheskoe Obozrenie"},{"key":"20739_B37","first-page":"227","article-title":"Phyllocnistis ramulicola sp. nov. (Lepidoptera: Gracillariidae) in England and Portugal.","volume":"58","author":"Langmaid","year":"2007","journal-title":"Entomologist\u2019s Gazette"},{"issue":"162","key":"20739_B38","first-page":"251","article-title":"A revision of the Phyllonorycter ulicicolella species group with description of a new species (Lepidoptera: Gracillariidae).","volume":"41","author":"La\u0161t\u016fvka","year":"2013","journal-title":"SHILAP Revista Lepidopterologia"},{"key":"20739_B39","doi-asserted-by":"publisher","DOI":"10.3791\/3923"},{"issue":"4","key":"20739_B40","first-page":"412","article-title":"A new species of Phyllocnistidae from China.","volume":"28","author":"Liu","year":"1985","journal-title":"Acta Entomologica Sinica"},{"issue":"1","key":"20739_B41","first-page":"85","article-title":"Two new species of Phyllocnistidae from South China.","volume":"32","author":"Liu","year":"1989","journal-title":"Acta Entomologica Sinica"},{"key":"20739_B42","doi-asserted-by":"publisher","DOI":"10.3897\/zookeys.686.13680"},{"key":"20739_B43","doi-asserted-by":"publisher","DOI":"10.1006\/mpev.2001.0993"},{"key":"20739_B44","first-page":"244","article-title":"Mining Lepidoptera of genus Phyllocnistis Z. (Lepidoptera, Phyllocnistidae) of fauna of the USSR.","volume":"34","author":"Martynova","year":"1955","journal-title":"Entomologicheskoe Obozrenie"},{"issue":"6","key":"20739_B45","first-page":"161","article-title":"Exotic Microlepidoptera.","volume":"4","author":"Meyrick","year":"1931","journal-title":"Exotic Microlepidoptera (Marlborough)"},{"key":"20739_B46","year":"2017"},{"key":"20739_B47","doi-asserted-by":"publisher","DOI":"10.1111\/j.1479-8298.2005.00120.x"},{"key":"20739_B48","author":"Pato\u010dka","year":"2005","journal-title":"Lepidoptera Pupae: Central European Species."},{"key":"20739_B49","author":"Ratnasingham","year":"2007"},{"key":"20739_B50","doi-asserted-by":"publisher","DOI":"10.1371\/journal.pone.0066213"},{"key":"20739_B51","doi-asserted-by":"publisher","DOI":"10.1371\/journal.pone.0078107"},{"issue":"2","key":"20739_B52","first-page":"422","article-title":"New species of mining moths of the families Bacculatricidae [sic] and Phyllocnistidae (Lepidoptera) from Primorye Territory.","volume":"71","author":"Seksyaeva","year":"1992","journal-title":"Entomologicheskoe Obozrenie"},{"key":"20739_B53","first-page":"429","article-title":"Phyllocnistidae.","author":"Seksyaeva","year":"1997","journal-title":"Vol. V. Trichoptera and Lepidoptera. Pt 1. Dal\u2019nauka, Vladivostok"},{"key":"20739_B54","author":"Sinev","year":"2008"},{"key":"20739_B55","doi-asserted-by":"publisher","DOI":"10.1093\/bioinformatics\/btu033"},{"key":"20739_B56","year":"2013"},{"key":"20739_B57","first-page":"3","article-title":"Mining insects of Eastern Siberia.","author":"Tomilova","year":"1973","journal-title":"The publishing house of Irkutsk university, Irkutsk"},{"key":"20739_B58","first-page":"147","article-title":"Phyllonorycter species from Palaearctic region feeding on Rosaceae (Lepi- doptera, Gracillariidae). Bollettino del Museo Civico di Storia Naturale di Verona.","volume":"31","author":"Triberti","year":"2007","journal-title":"Botanica Zoologia"},{"key":"20739_B59","doi-asserted-by":"publisher","DOI":"10.2307\/25065525"}],"container-title":"ZooKeys","original-title":[],"link":[{"URL":"https:\/\/zookeys.pensoft.net\/lib\/ajax_srv\/article_elements_srv.php?action=download_pdf&item_id=20739","content-type":"application\/pdf","content-version":"vor","intended-application":"text-mining"},{"URL":"https:\/\/zookeys.pensoft.net\/lib\/ajax_srv\/article_elements_srv.php?action=download_xml&item_id=20739","content-type":"application\/xml","content-version":"vor","intended-application":"text-mining"},{"URL":"https:\/\/zookeys.pensoft.net\/article_preview.php?id=20739&skip_redirect=1","content-type":"unspecified","content-version":"vor","intended-application":"similarity-checking"}],"deposited":{"date-parts":[[2018,2,8]],"date-time":"2018-02-08T09:56:09Z","timestamp":1518083769000},"score":1,"resource":{"primary":{"URL":"https:\/\/zookeys.pensoft.net\/articles.php?id=20739"}},"subtitle":[],"short-title":[],"issued":{"date-parts":[[2018,2,8]]},"references-count":59,"URL":"http:\/\/dx.doi.org\/10.3897\/zookeys.736.20739","relation":{},"ISSN":["1313-2970","1313-2989"],"subject":[],"container-title-short":"ZK","published":{"date-parts":[[2018,2,8]]}}